{
  "products": [
    {
      "id": 1,
      "name": "Hoodie",
      "description": "Descr1",
      "imageUrl": "https://www.pasnormalstudios.com/shared/16/615/pas-normal-studios-logo-hoodie-black_1180w.jpg",
      "price": 1500
    },
    {
      "id": 2,
      "name": "T-shirt",
      "description": "Descr2",
      "imageUrl": "https://www.jackjones.com/dw/image/v2/ABBT_PRD/on/demandware.static/-/Sites-pim-catalog/default/dw54431423/pim-static/large/12059219_OPTWHITE_002_ProductLarge.jpg?sw=685",
      "price": 500
    },
    {
      "id": 3,
      "name": "Pants",
      "description": "Descr3",
      "imageUrl": "https://ufpro.com/storage/app/media/Product%20Images/Pants/P-40%20Urban/Product%20images/Kangaroo/p40-urban-pants-kangaroo-hero-2019-610.jpg",
      "price": 800
    },
    {
      "id": 4,
      "name": "Shoes",
      "description": "Descr4",
      "imageUrl": "https://assets.ajio.com/medias/sys_master/root/h0e/h57/14092954894366/-473Wx593H-460455972-black-MODEL.jpg",
      "price": 1100
    }
  ],
  "posts": [
    {
      "id": 1,
      "title": "json-server",
      "author": "typicode"
    }
  ],
  "comments": [
    {
      "id": 1,
      "body": "some comment",
      "postId": 1
    }
  ],
  "profile": {
    "name": "typicode"
  },
  "wishlist": [],
  "cart": [
    {
      "product": {
        "id": 3,
        "name": "Pants",
        "description": "Descr3",
        "imageUrl": "https://ufpro.com/storage/app/media/Product%20Images/Pants/P-40%20Urban/Product%20images/Kangaroo/p40-urban-pants-kangaroo-hero-2019-610.jpg",
        "price": 800
      },
      "id": 1
    },
    {
      "product": {
        "id": 3,
        "name": "Pants",
        "description": "Descr3",
        "imageUrl": "https://ufpro.com/storage/app/media/Product%20Images/Pants/P-40%20Urban/Product%20images/Kangaroo/p40-urban-pants-kangaroo-hero-2019-610.jpg",
        "price": 800
      },
      "id": 2
    },
    {
      "product": {
        "id": 3,
        "name": "Pants",
        "description": "Descr3",
        "imageUrl": "https://ufpro.com/storage/app/media/Product%20Images/Pants/P-40%20Urban/Product%20images/Kangaroo/p40-urban-pants-kangaroo-hero-2019-610.jpg",
        "price": 800
      },
      "id": 3
    },
    {
      "product": {
        "id": 1,
        "name": "Hoodie",
        "description": "Descr1",
        "imageUrl": "https://www.pasnormalstudios.com/shared/16/615/pas-normal-studios-logo-hoodie-black_1180w.jpg",
        "price": 1500
      },
      "id": 4
    },
    {
      "product": {
        "id": 1,
        "name": "Hoodie",
        "description": "Descr1",
        "imageUrl": "https://www.pasnormalstudios.com/shared/16/615/pas-normal-studios-logo-hoodie-black_1180w.jpg",
        "price": 1500
      },
      "id": 5
    }
  ]
}